pytint/__init__.py
pytint/__init__.pyi
pytint/colors.py
pytint/colors.pyi
pytint/pytint.py
pytint/pytint.pyi
pytint/svg_tool.py
pytint/svg_tool.pyi
pytint/tint.py
pytint/tint.pyi
pytint-1.0.3.dist-info/LICENSE
pytint-1.0.3.dist-info/METADATA
pytint-1.0.3.dist-info/WHEEL
pytint-1.0.3.dist-info/RECORD
