Metadata-Version: 2.1
Name: pytint
Version: 1.0.3
Summary: python package to colorize envy icons, themes, etc.
Home-page: https://codeberg.org/toufy/pytint
License: GPL-3.0-or-later
Author: toufy
Author-email: ar.toufic@protonmail.com
Requires-Python: >=3.11,<4.0
Classifier: License :: OSI Approved :: GNU General Public License v3 or later (GPLv3+)
Classifier: Programming Language :: Python :: 3
Classifier: Programming Language :: Python :: 3.11
Requires-Dist: python-magic (>=0.4.27,<0.5.0)
Project-URL: Repository, https://codeberg.org/toufy/pytint
